README.md
setup.py
CaptainSoul.egg-info/PKG-INFO
CaptainSoul.egg-info/SOURCES.txt
CaptainSoul.egg-info/dependency_links.txt
CaptainSoul.egg-info/entry_points.txt
CaptainSoul.egg-info/requires.txt
CaptainSoul.egg-info/top_level.txt
CaptainSoul.egg-info/zip-safe
cptsoul/__init__.py
cptsoul/__main__.py
cptsoul/addcontactwindow.py
cptsoul/common.py
cptsoul/entry_points.py
cptsoul/htmltextview.py
cptsoul/manager.py
cptsoul/notify.py
cptsoul/systray.py
cptsoul/chatwindow/__init__.py
cptsoul/chatwindow/chatentry.py
cptsoul/chatwindow/chatstatus.py
cptsoul/chatwindow/chatview.py
cptsoul/config/__init__.py
cptsoul/config/configfile.py
cptsoul/config/configtypes.py
cptsoul/debugwindow/__init__.py
cptsoul/debugwindow/debugentry.py
cptsoul/debugwindow/debugview.py
cptsoul/downloadmanager/__init__.py
cptsoul/downloadmanager/askfilewindow.py
cptsoul/downloadmanager/downloadlist.py
cptsoul/downloadmanager/tools.py
cptsoul/downloadmanager/uploadlist.py
cptsoul/getfile/__init__.py
cptsoul/getfile/factory.py
cptsoul/getfile/protocol.py
cptsoul/icons/__init__.py
cptsoul/icons/epitech.png
cptsoul/icons/green.png
cptsoul/icons/orange.png
cptsoul/icons/red.png
cptsoul/icons/shield.png
cptsoul/icons/void.png
cptsoul/mainwindow/__init__.py
cptsoul/mainwindow/loginlist.py
cptsoul/mainwindow/mainstatus.py
cptsoul/mainwindow/toolbar.py
cptsoul/mainwindow/watchlist.py
cptsoul/netsoul/__init__.py
cptsoul/netsoul/tools.py
cptsoul/sendfile/__init__.py
cptsoul/sendfile/factory.py
cptsoul/sendfile/producer.py
cptsoul/sendfile/protocol.py
cptsoul/settingswindow/__init__.py