Metadata-Version: 1.0
Name: CaptainSoul
Version: 0.1.9
Summary: Netsoul client with pygtk and twisted
Home-page: https://github.com/dennajort/CaptainSoul
Author: dennajort
Author-email: UNKNOWN
License: UNKNOWN
Platform: UNKNOWN
